{
    "appKeys": {},
    "capabilities": [
        ""
    ],
    "companyName": "fcanas@gmail.com",
    "longName": "Kite",
    "projectType": "pebblejs",
    "resources": {
        "media": [
            {
                "file": "images/really_good.png",
                "menuIcon": true,
                "name": "IMAGE_MENU_ICON",
                "type": "png"
            },
            {
                "file": "images/really_good.png",
                "name": "IMAGE_LOGO_SPLASH",
                "type": "png"
            },
            {
                "file": "images/really_good.png",
                "name": "IMAGE_TILE_SPLASH",
                "type": "png"
            }
        ]
    },
    "shortName": "Kite",
    "uuid": "63997a49-31bb-48b1-9a58-15989de861a9",
    "versionCode": 1,
    "versionLabel": "1.0",
    "watchapp": {
        "watchface": false
    }
}
